{
  "diagram":"SequenceDiagram",
  "nodes":[
    {
      "x":0,
      "y":0,
      "openBottom":false,
      "id":1,
      "type":"CallNode"
    },
    {
      "children":[
        1
      ],
      "x":130,
      "name":"A",
      "y":20,
      "id":0,
      "type":"ImplicitParameterNode"
    },
    {
      "children":[
        5
      ],
      "x":720,
      "name":"C",
      "y":40,
      "id":4,
      "type":"ImplicitParameterNode"
    },
    {
      "children":[
        3
      ],
      "x":420,
      "name":"B",
      "y":30,
      "id":2,
      "type":"ImplicitParameterNode"
    },
    {
      "x":0,
      "y":0,
      "openBottom":false,
      "id":3,
      "type":"CallNode"
    },
    {
      "x":0,
      "y":0,
      "openBottom":false,
      "id":5,
      "type":"CallNode"
    }
  ],
  "edges":[
    {
      "middleLabel":"call1",
      "start":1,
      "end":3,
      "type":"CallEdge",
      "signal":false
    },
    {
      "middleLabel":"result1",
      "start":3,
      "end":1,
      "type":"ReturnEdge"
    },
    {
      "middleLabel":"call2",
      "start":3,
      "end":5,
      "type":"CallEdge",
      "signal":false
    },
    {
      "middleLabel":"result2",
      "start":5,
      "end":3,
      "type":"ReturnEdge"
    }
  ],
  "version":"2.2"
}